flask_funktional.py
setup.py
flask_funktional.egg-info/PKG-INFO
flask_funktional.egg-info/SOURCES.txt
flask_funktional.egg-info/dependency_links.txt
flask_funktional.egg-info/not-zip-safe
flask_funktional.egg-info/requires.txt
flask_funktional.egg-info/top_level.txt