Metadata-Version: 1.1
Name: flask-funktional
Version: 0.0.1
Summary: 
